azure/mgmt/securitydevops/__init__.py
azure/mgmt/securitydevops/_configuration.py
azure/mgmt/securitydevops/_microsoft_security_dev_ops.py
azure/mgmt/securitydevops/_patch.py
azure/mgmt/securitydevops/_serialization.py
azure/mgmt/securitydevops/_vendor.py
azure/mgmt/securitydevops/_version.py
azure/mgmt/securitydevops/py.typed
azure/mgmt/securitydevops/aio/__init__.py
azure/mgmt/securitydevops/aio/_configuration.py
azure/mgmt/securitydevops/aio/_microsoft_security_dev_ops.py
azure/mgmt/securitydevops/aio/_patch.py
azure/mgmt/securitydevops/aio/operations/__init__.py
azure/mgmt/securitydevops/aio/operations/_azure_dev_ops_connector_operations.py
azure/mgmt/securitydevops/aio/operations/_azure_dev_ops_connector_stats_operations.py
azure/mgmt/securitydevops/aio/operations/_azure_dev_ops_org_operations.py
azure/mgmt/securitydevops/aio/operations/_azure_dev_ops_project_operations.py
azure/mgmt/securitydevops/aio/operations/_azure_dev_ops_repo_operations.py
azure/mgmt/securitydevops/aio/operations/_git_hub_connector_operations.py
azure/mgmt/securitydevops/aio/operations/_git_hub_connector_stats_operations.py
azure/mgmt/securitydevops/aio/operations/_git_hub_owner_operations.py
azure/mgmt/securitydevops/aio/operations/_git_hub_repo_operations.py
azure/mgmt/securitydevops/aio/operations/_operations.py
azure/mgmt/securitydevops/aio/operations/_patch.py
azure/mgmt/securitydevops/models/__init__.py
azure/mgmt/securitydevops/models/_microsoft_security_dev_ops_enums.py
azure/mgmt/securitydevops/models/_models_py3.py
azure/mgmt/securitydevops/models/_patch.py
azure/mgmt/securitydevops/operations/__init__.py
azure/mgmt/securitydevops/operations/_azure_dev_ops_connector_operations.py
azure/mgmt/securitydevops/operations/_azure_dev_ops_connector_stats_operations.py
azure/mgmt/securitydevops/operations/_azure_dev_ops_org_operations.py
azure/mgmt/securitydevops/operations/_azure_dev_ops_project_operations.py
azure/mgmt/securitydevops/operations/_azure_dev_ops_repo_operations.py
azure_mgmt_securitydevops-1.0.0b2.dist-info/LICENSE
azure_mgmt_securitydevops-1.0.0b2.dist-info/METADATA
azure_mgmt_securitydevops-1.0.0b2.dist-info/WHEEL
azure_mgmt_securitydevops-1.0.0b2.dist-info/top_level.txt
azure_mgmt_securitydevops-1.0.0b2.dist-info/RECORD
